aiologfields.py
aiologfields-2019.12.1.dist-info/LICENSE
aiologfields-2019.12.1.dist-info/WHEEL
aiologfields-2019.12.1.dist-info/METADATA
aiologfields-2019.12.1.dist-info/RECORD
