Metadata-Version: 2.1
Name: aiologfields
Version: 2019.12.1
Summary: aiologfields: inject Task-context-fields into loggers
Home-page: https://github.com/cjrh/aiologfields
License: UNKNOWN
Author: Caleb Hattingh
Author-email: caleb.hattingh@gmail.com
Classifier: License :: OSI Approved :: Apache Software License
Classifier: Natural Language :: English
Classifier: Programming Language :: Python
Classifier: Programming Language :: Python :: 3.5
Classifier: Programming Language :: Python :: 3.6
Classifier: Programming Language :: Python :: 3.7
Classifier: Programming Language :: Python :: 3.8
Classifier: Operating System :: OS Independent
Requires-Dist: pytest ; extra == "dev"
Requires-Dist: pytest-cov ; extra == "dev"
Provides-Extra: dev
